zennit/__init__.py
zennit/attribution.py
zennit/canonizers.py
zennit/cmap.py
zennit/composites.py
zennit/core.py
zennit/image.py
zennit/layer.py
zennit/rules.py
zennit/torchvision.py
zennit/types.py
zennit/version.py
zennit-1.0.0.dist-info/METADATA
zennit-1.0.0.dist-info/WHEEL
zennit-1.0.0.dist-info/licenses/COPYING
zennit-1.0.0.dist-info/licenses/COPYING.LESSER
zennit-1.0.0.dist-info/RECORD
