Metadata-Version: 2.4
Name: zennit
Version: 1.0.0
Summary: Attribution of Neural Networks using PyTorch
Project-URL: Documentation, https://zennit.readthedocs.io/en/latest/
Project-URL: Repository, https://github.com/chr5tphr/zennit.git
Project-URL: Issues, https://github.com/chr5tphr/zennit/issues
Author-email: "Christopher J. Anders" <contact@cjanders.de>, Sebastian Lapuschkin <sebastian.lapuschkin@hhi.fraunhofer.de>, Pattarawat Chormai <pat.chormai@gmail.com>
Maintainer-email: "Christopher J. Anders" <contact@cjanders.de>
License-Expression: GPL-3.0-or-later AND LGPL-3.0-or-later
License-File: COPYING
License-File: COPYING.LESSER
Keywords: Artificial Intelligence,Deep Learning,Explainable AI,Feature Attribution,Interpretability,Machine Learning,XAI
Classifier: Development Status :: 3 - Alpha
Classifier: Intended Audience :: Science/Research
Classifier: License :: OSI Approved :: GNU General Public License v3 or later (GPLv3+)
Classifier: License :: OSI Approved :: GNU Lesser General Public License v3 or later (LGPLv3+)
Classifier: Natural Language :: English
Classifier: Programming Language :: Python :: 3.11
Classifier: Programming Language :: Python :: 3.12
Classifier: Programming Language :: Python :: 3.13
Classifier: Topic :: Scientific/Engineering :: Artificial Intelligence
Requires-Python: >=3.11.11
Requires-Dist: click
Requires-Dist: numpy
Requires-Dist: pillow
Requires-Dist: torch<3.0.0,>=2.0.0
Requires-Dist: torchvision
